filestore/__init__.py
filestore/filestore.py
py_filestore-1.1.0.dist-info/LICENSE.txt
py_filestore-1.1.0.dist-info/METADATA
py_filestore-1.1.0.dist-info/WHEEL
py_filestore-1.1.0.dist-info/top_level.txt
py_filestore-1.1.0.dist-info/RECORD
