Metadata-Version: 2.1
Name: py-filestore
Version: 1.1.0
Summary: A python package that implements a static dictionary as a file system.
Home-page: https://github.com/Caddox/pyfilestore
Author: Rhys Salkind
License: UNKNOWN
Platform: UNKNOWN
Classifier: Programming Language :: Python :: 3
Classifier: License :: OSI Approved :: MIT License
